final_project_traffic.v
`timescale 1s / 1ms

module traffic_controller(
    input clk,
    input rst,
    input Emergency_Left,
    input Emergency_Right,
    output reg [1:0] T1_light,
    output reg [1:0] T2_light,
    output reg Buzzer_T1,
    output reg Buzzer_T2
);

    parameter RED    = 2'b00;
    parameter GREEN  = 2'b01;
    parameter YELLOW = 2'b10;

    reg [1:0] T1_state = GREEN;
    reg [1:0] T2_state = GREEN;
    reg [7:0] T1_timer = 0;
    reg [7:0] T2_timer = 0;

    reg [15:0] current_time = 0;
    reg [15:0] pause_until_T1 = 0;
    reg [15:0] pause_until_T2 = 0;

    wire pause_T1 = (current_time < pause_until_T1);
    wire pause_T2 = (current_time < pause_until_T2);

    always @(posedge clk or posedge rst) begin
        if (rst) begin
            T1_state <= GREEN;
            T2_state <= GREEN;
            T1_timer <= 0;
            T2_timer <= 0;
            pause_until_T1 <= 0;
            pause_until_T2 <= 0;
            current_time <= 0;
        end else begin
            current_time <= current_time + 1;

            if (Emergency_Left) begin
                if (pause_until_T1 < current_time + 11)
                    pause_until_T1 <= current_time + 11;
            end

            if (Emergency_Right) begin
                if (pause_until_T1 < current_time + 11)
                    pause_until_T1 <= current_time + 11;
                if (pause_until_T2 < current_time + 11)
                    pause_until_T2 <= current_time + 11;
            end

            if (!pause_T1) begin
                case (T1_state)
                    RED: begin
                        if (T1_timer < 59) T1_timer <= T1_timer + 1;
                        else begin
                            T1_state <= GREEN;
                            T1_timer <= 0;
                        end
                    end
                    GREEN: begin
                        if (T1_timer < 24) T1_timer <= T1_timer + 1;
                        else begin
                            T1_state <= YELLOW;
                            T1_timer <= 0;
                        end
                    end
                    YELLOW: begin
                        if (T1_timer < 4) T1_timer <= T1_timer + 1;
                        else begin
                            T1_state <= RED;
                            T1_timer <= 0;
                        end
                    end
                endcase
            end

            if (!pause_T2) begin
                case (T2_state)
                    RED: begin
                        if (T2_timer < 59) T2_timer <= T2_timer + 1;
                        else begin
                            T2_state <= GREEN;
                            T2_timer <= 0;
                        end
                    end
                    GREEN: begin
                        if (T2_timer < 24) T2_timer <= T2_timer + 1;
                        else begin
                            T2_state <= YELLOW;
                            T2_timer <= 0;
                        end
                    end
                    YELLOW: begin
                        if (T2_timer < 4) T2_timer <= T2_timer + 1;
                        else begin
                            T2_state <= RED;
                            T2_timer <= 0;
                        end
                    end
                endcase
            end
        end
    end

    always @(*) begin
        T1_light = pause_T1 ? RED : T1_state;
        T2_light = pause_T2 ? RED : T2_state;

        Buzzer_T1 = (!pause_T1 && T1_state == RED && T1_timer >= 55);
        Buzzer_T2 = (!pause_T2 && T2_state == RED && T2_timer >= 55);
    end

endmodule

testbench.v
`timescale 1s / 1ms

module tb_traffic_controller;

    reg clk = 0;
    reg rst = 1;
    reg Emergency_Left = 0;
    reg Emergency_Right = 0;

    wire [1:0] T1_light;
    wire [1:0] T2_light;
    wire Buzzer_T1, Buzzer_T2;

    traffic_controller uut (
        .clk(clk),
        .rst(rst),
        .Emergency_Left(Emergency_Left),
        .Emergency_Right(Emergency_Right),
        .T1_light(T1_light),
        .T2_light(T2_light),
        .Buzzer_T1(Buzzer_T1),
        .Buzzer_T2(Buzzer_T2)
    );

    // Clock generation: 1 Hz
    initial forever #0.5 clk = ~clk;

    // Display helper
    task print_state;
        input integer t;
        begin
            $display("Time: %0d | T1: %s | T2: %s | Walk_1: %b | Walk_2: %b | E_L: %b | E_R: %b",
                t,
                (T1_light == 2'b00) ? "RED   " :
                (T1_light == 2'b01) ? "GREEN " :
                (T1_light == 2'b10) ? "YELLOW" : "UNK   ",
                (T2_light == 2'b00) ? "RED   " :
                (T2_light == 2'b01) ? "GREEN " :
                (T2_light == 2'b10) ? "YELLOW" : "UNK   ",
                Buzzer_T1,
                Buzzer_T2,
                Emergency_Left,
                Emergency_Right
            );
        end
    endtask

    // Reset and test sequence
    initial begin
        $dumpfile("traffic_controller.vcd");
        $dumpvars(0, tb_traffic_controller);
        $display("=== Traffic Controller Testbench Start ===");
        rst = 0; // Deassert reset after 1s
    end

    integer i = 1;
    always @(posedge clk) begin
        // Trigger Emergency Left during T1 GREEN (starts at time ~1s)
        if (i == 2) Emergency_Left = 1;
        if (i == 6) begin
            Emergency_Right = 1;
            Emergency_Left = 1;
        end
        if( i == 7) begin
            Emergency_Right = 0;
            Emergency_Left = 0;
        end

        if(i == 36) begin
            Emergency_Right = 1;
        end
        if(i == 37) begin
            Emergency_Right = 0;
        end

        if(i == 51) begin
            Emergency_Left = 1;
        end
        if(i == 52) begin
            Emergency_Left = 0;
        end
        if(i == 108) begin
            Emergency_Right = 1;
        end
        if(i == 109) begin
            Emergency_Right = 0;
        end

        if(i == 119) begin
            Emergency_Left = 1;
        end
        if(i == 120) begin
            Emergency_Left = 0;
        end

        print_state(i);

        // Stop after 150 seconds
        if (i == 150) begin
            $display("=== Traffic Controller Testbench Complete ===");
            $finish;
        end
        i = i + 1;
    end

endmodule

traffic_controller.vcd
$date
	Wed May 07 11:34:27 2025
$end
$version
	Icarus Verilog
$end
$timescale
	1ms
$end
$scope module tb_traffic_controller $end
$var wire 2 ! T2_light [1:0] $end
$var wire 2 " T1_light [1:0] $end
$var wire 1 # Buzzer_T2 $end
$var wire 1 $ Buzzer_T1 $end
$var reg 1 % Emergency_Left $end
$var reg 1 & Emergency_Right $end
$var reg 1 ' clk $end
$var reg 1 ( rst $end
$var integer 32 ) i [31:0] $end
$scope module uut $end
$var wire 1 % Emergency_Left $end
$var wire 1 & Emergency_Right $end
$var wire 1 ' clk $end
$var wire 1 ( rst $end
$var wire 1 * pause_T2 $end
$var wire 1 + pause_T1 $end
$var parameter 2 , GREEN $end
$var parameter 2 - RED $end
$var parameter 2 . YELLOW $end
$var reg 1 $ Buzzer_T1 $end
$var reg 1 # Buzzer_T2 $end
$var reg 2 / T1_light [1:0] $end
$var reg 2 0 T1_state [1:0] $end
$var reg 8 1 T1_timer [7:0] $end
$var reg 2 2 T2_light [1:0] $end
$var reg 2 3 T2_state [1:0] $end
$var reg 8 4 T2_timer [7:0] $end
$var reg 16 5 current_time [15:0] $end
$var reg 16 6 pause_until_T1 [15:0] $end
$var reg 16 7 pause_until_T2 [15:0] $end
$upscope $end
$scope task print_state $end
$var integer 32 8 t [31:0] $end
$upscope $end
$upscope $end
$enddefinitions $end
$comment Show the parameter values. $end
$dumpall
b10 .
b0 -
b1 ,
$end
#0
$dumpvars
bx 8
b0 7
b0 6
b0 5
b0 4
b1 3
bx 2
b0 1
b1 0
bx /
0+
0*
b1 )
0(
0'
0&
0%
x$
x#
bx "
bx !
$end
#500
0#
0$
b1 !
b1 2
b1 "
b1 /
b1 4
b1 1
b1 5
b10 )
b1 8
1'
#1000
0'
#1500
b0 "
b0 /
b10 4
b10 1
1+
b1100 6
b10 5
b11 )
b10 8
1%
1'
#2000
0'
#2500
b11 4
b1101 6
b11 5
b100 )
b11 8
1'
#3000
0'
#3500
b100 4
b1110 6
b100 5
b101 )
b100 8
1'
#4000
0'
#4500
b101 4
b1111 6
b101 5
b110 )
b101 8
1'
#5000
0'
#5500
b0 !
b0 2
b110 4
1*
b10000 7
b10000 6
b110 5
b111 )
b110 8
1&
1'
#6000
0'
#6500
b111 5
b1000 )
b111 8
0%
0&
1'
#7000
0'
#7500
b1000 5
b1001 )
b1000 8
1'
#8000
0'
#8500
b1001 5
b1010 )
b1001 8
1'
#9000
0'
#9500
b1010 5
b1011 )
b1010 8
1'
#10000
0'
#10500
b1011 5
b1100 )
b1011 8
1'
#11000
0'
#11500
b1100 5
b1101 )
b1100 8
1'
#12000
0'
#12500
b1101 5
b1110 )
b1101 8
1'
#13000
0'
#13500
b1110 5
b1111 )
b1110 8
1'
#14000
0'
#14500
b1111 5
b10000 )
b1111 8
1'
#15000
0'
#15500
b1 !
b1 2
b1 "
b1 /
0+
0*
b10000 5
b10001 )
b10000 8
1'
#16000
0'
#16500
b111 4
b11 1
b10001 5
b10010 )
b10001 8
1'
#17000
0'
#17500
b1000 4
b100 1
b10010 5
b10011 )
b10010 8
1'
#18000
0'
#18500
b1001 4
b101 1
b10011 5
b10100 )
b10011 8
1'
#19000
0'
#19500
b1010 4
b110 1
b10100 5
b10101 )
b10100 8
1'
#20000
0'
#20500
b1011 4
b111 1
b10101 5
b10110 )
b10101 8
1'
#21000
0'
#21500
b1100 4
b1000 1
b10110 5
b10111 )
b10110 8
1'
#22000
0'
#22500
b1101 4
b1001 1
b10111 5
b11000 )
b10111 8
1'
#23000
0'
#23500
b1110 4
b1010 1
b11000 5
b11001 )
b11000 8
1'
#24000
0'
#24500
b1111 4
b1011 1
b11001 5
b11010 )
b11001 8
1'
#25000
0'
#25500
b10000 4
b1100 1
b11010 5
b11011 )
b11010 8
1'
#26000
0'
#26500
b10001 4
b1101 1
b11011 5
b11100 )
b11011 8
1'
#27000
0'
#27500
b10010 4
b1110 1
b11100 5
b11101 )
b11100 8
1'
#28000
0'
#28500
b10011 4
b1111 1
b11101 5
b11110 )
b11101 8
1'
#29000
0'
#29500
b10100 4
b10000 1
b11110 5
b11111 )
b11110 8
1'
#30000
0'
#30500
b10101 4
b10001 1
b11111 5
b100000 )
b11111 8
1'
#31000
0'
#31500
b10110 4
b10010 1
b100000 5
b100001 )
b100000 8
1'
#32000
0'
#32500
b10111 4
b10011 1
b100001 5
b100010 )
b100001 8
1'
#33000
0'
#33500
b11000 4
b10100 1
b100010 5
b100011 )
b100010 8
1'
#34000
0'
#34500
b10 !
b10 2
b0 4
b10 3
b10101 1
b100011 5
b100100 )
b100011 8
1'
#35000
0'
#35500
b0 !
b0 2
b0 "
b0 /
b1 4
b10110 1
1*
b101110 7
1+
b101110 6
b100100 5
b100101 )
b100100 8
1&
1'
#36000
0'
#36500
b100101 5
b100110 )
b100101 8
0&
1'
#37000
0'
#37500
b100110 5
b100111 )
b100110 8
1'
#38000
0'
#38500
b100111 5
b101000 )
b100111 8
1'
#39000
0'
#39500
b101000 5
b101001 )
b101000 8
1'
#40000
0'
#40500
b101001 5
b101010 )
b101001 8
1'
#41000
0'
#41500
b101010 5
b101011 )
b101010 8
1'
#42000
0'
#42500
b101011 5
b101100 )
b101011 8
1'
#43000
0'
#43500
b101100 5
b101101 )
b101100 8
1'
#44000
0'
#44500
b101101 5
b101110 )
b101101 8
1'
#45000
0'
#45500
b10 !
b10 2
b1 "
b1 /
0+
0*
b101110 5
b101111 )
b101110 8
1'
#46000
0'
#46500
b10 4
b10111 1
b101111 5
b110000 )
b101111 8
1'
#47000
0'
#47500
b11 4
b11000 1
b110000 5
b110001 )
b110000 8
1'
#48000
0'
#48500
b10 "
b10 /
b100 4
b0 1
b10 0
b110001 5
b110010 )
b110001 8
1'
#49000
0'
#49500
b0 !
b0 2
b0 4
b0 3
b1 1
b110010 5
b110011 )
b110010 8
1'
#50000
0'
#50500
b0 "
b0 /
b1 4
b10 1
1+
b111101 6
b110011 5
b110100 )
b110011 8
1%
1'
#51000
0'
#51500
b10 4
b110100 5
b110101 )
b110100 8
0%
1'
#52000
0'
#52500
b11 4
b110101 5
b110110 )
b110101 8
1'
#53000
0'
#53500
b100 4
b110110 5
b110111 )
b110110 8
1'
#54000
0'
#54500
b101 4
b110111 5
b111000 )
b110111 8
1'
#55000
0'
#55500
b110 4
b111000 5
b111001 )
b111000 8
1'
#56000
0'
#56500
b111 4
b111001 5
b111010 )
b111001 8
1'
#57000
0'
#57500
b1000 4
b111010 5
b111011 )
b111010 8
1'
#58000
0'
#58500
b1001 4
b111011 5
b111100 )
b111011 8
1'
#59000
0'
#59500
b1010 4
b111100 5
b111101 )
b111100 8
1'
#60000
0'
#60500
b10 "
b10 /
b1011 4
0+
b111101 5
b111110 )
b111101 8
1'
#61000
0'
#61500
b1100 4
b11 1
b111110 5
b111111 )
b111110 8
1'
#62000
0'
#62500
b1101 4
b100 1
b111111 5
b1000000 )
b111111 8
1'
#63000
0'
#63500
b0 "
b0 /
b1110 4
b0 1
b0 0
b1000000 5
b1000001 )
b1000000 8
1'
#64000
0'
#64500
b1111 4
b1 1
b1000001 5
b1000010 )
b1000001 8
1'
#65000
0'
#65500
b10000 4
b10 1
b1000010 5
b1000011 )
b1000010 8
1'
#66000
0'
#66500
b10001 4
b11 1
b1000011 5
b1000100 )
b1000011 8
1'
#67000
0'
#67500
b10010 4
b100 1
b1000100 5
b1000101 )
b1000100 8
1'
#68000
0'
#68500
b10011 4
b101 1
b1000101 5
b1000110 )
b1000101 8
1'
#69000
0'
#69500
b10100 4
b110 1
b1000110 5
b1000111 )
b1000110 8
1'
#70000
0'
#70500
b10101 4
b111 1
b1000111 5
b1001000 )
b1000111 8
1'
#71000
0'
#71500
b10110 4
b1000 1
b1001000 5
b1001001 )
b1001000 8
1'
#72000
0'
#72500
b10111 4
b1001 1
b1001001 5
b1001010 )
b1001001 8
1'
#73000
0'
#73500
b11000 4
b1010 1
b1001010 5
b1001011 )
b1001010 8
1'
#74000
0'
#74500
b11001 4
b1011 1
b1001011 5
b1001100 )
b1001011 8
1'
#75000
0'
#75500
b11010 4
b1100 1
b1001100 5
b1001101 )
b1001100 8
1'
#76000
0'
#76500
b11011 4
b1101 1
b1001101 5
b1001110 )
b1001101 8
1'
#77000
0'
#77500
b11100 4
b1110 1
b1001110 5
b1001111 )
b1001110 8
1'
#78000
0'
#78500
b11101 4
b1111 1
b1001111 5
b1010000 )
b1001111 8
1'
#79000
0'
#79500
b11110 4
b10000 1
b1010000 5
b1010001 )
b1010000 8
1'
#80000
0'
#80500
b11111 4
b10001 1
b1010001 5
b1010010 )
b1010001 8
1'
#81000
0'
#81500
b100000 4
b10010 1
b1010010 5
b1010011 )
b1010010 8
1'
#82000
0'
#82500
b100001 4
b10011 1
b1010011 5
b1010100 )
b1010011 8
1'
#83000
0'
#83500
b100010 4
b10100 1
b1010100 5
b1010101 )
b1010100 8
1'
#84000
0'
#84500
b100011 4
b10101 1
b1010101 5
b1010110 )
b1010101 8
1'
#85000
0'
#85500
b100100 4
b10110 1
b1010110 5
b1010111 )
b1010110 8
1'
#86000
0'
#86500
b100101 4
b10111 1
b1010111 5
b1011000 )
b1010111 8
1'
#87000
0'
#87500
b100110 4
b11000 1
b1011000 5
b1011001 )
b1011000 8
1'
#88000
0'
#88500
b100111 4
b11001 1
b1011001 5
b1011010 )
b1011001 8
1'
#89000
0'
#89500
b101000 4
b11010 1
b1011010 5
b1011011 )
b1011010 8
1'
#90000
0'
#90500
b101001 4
b11011 1
b1011011 5
b1011100 )
b1011011 8
1'
#91000
0'
#91500
b101010 4
b11100 1
b1011100 5
b1011101 )
b1011100 8
1'
#92000
0'
#92500
b101011 4
b11101 1
b1011101 5
b1011110 )
b1011101 8
1'
#93000
0'
#93500
b101100 4
b11110 1
b1011110 5
b1011111 )
b1011110 8
1'
#94000
0'
#94500
b101101 4
b11111 1
b1011111 5
b1100000 )
b1011111 8
1'
#95000
0'
#95500
b101110 4
b100000 1
b1100000 5
b1100001 )
b1100000 8
1'
#96000
0'
#96500
b101111 4
b100001 1
b1100001 5
b1100010 )
b1100001 8
1'
#97000
0'
#97500
b110000 4
b100010 1
b1100010 5
b1100011 )
b1100010 8
1'
#98000
0'
#98500
b110001 4
b100011 1
b1100011 5
b1100100 )
b1100011 8
1'
#99000
0'
#99500
b110010 4
b100100 1
b1100100 5
b1100101 )
b1100100 8
1'
#100000
0'
#100500
b110011 4
b100101 1
b1100101 5
b1100110 )
b1100101 8
1'
#101000
0'
#101500
b110100 4
b100110 1
b1100110 5
b1100111 )
b1100110 8
1'
#102000
0'
#102500
b110101 4
b100111 1
b1100111 5
b1101000 )
b1100111 8
1'
#103000
0'
#103500
b110110 4
b101000 1
b1101000 5
b1101001 )
b1101000 8
1'
#104000
0'
#104500
1#
b110111 4
b101001 1
b1101001 5
b1101010 )
b1101001 8
1'
#105000
0'
#105500
b111000 4
b101010 1
b1101010 5
b1101011 )
b1101010 8
1'
#106000
0'
#106500
b111001 4
b101011 1
b1101011 5
b1101100 )
b1101011 8
1'
#107000
0'
#107500
0#
b111010 4
b101100 1
1*
b1110110 7
1+
b1110110 6
b1101100 5
b1101101 )
b1101100 8
1&
1'
#108000
0'
#108500
b1101101 5
b1101110 )
b1101101 8
0&
1'
#109000
0'
#109500
b1101110 5
b1101111 )
b1101110 8
1'
#110000
0'
#110500
b1101111 5
b1110000 )
b1101111 8
1'
#111000
0'
#111500
b1110000 5
b1110001 )
b1110000 8
1'
#112000
0'
#112500
b1110001 5
b1110010 )
b1110001 8
1'
#113000
0'
#113500
b1110010 5
b1110011 )
b1110010 8
1'
#114000
0'
#114500
b1110011 5
b1110100 )
b1110011 8
1'
#115000
0'
#115500
b1110100 5
b1110101 )
b1110100 8
1'
#116000
0'
#116500
b1110101 5
b1110110 )
b1110101 8
1'
#117000
0'
#117500
1#
0+
0*
b1110110 5
b1110111 )
b1110110 8
1'
#118000
0'
#118500
b111011 4
b101101 1
1+
b10000001 6
b1110111 5
b1111000 )
b1110111 8
1%
1'
#119000
0'
#119500
0#
b1 !
b1 2
b0 4
b1 3
b1111000 5
b1111001 )
b1111000 8
0%
1'
#120000
0'
#120500
b1 4
b1111001 5
b1111010 )
b1111001 8
1'
#121000
0'
#121500
b10 4
b1111010 5
b1111011 )
b1111010 8
1'
#122000
0'
#122500
b11 4
b1111011 5
b1111100 )
b1111011 8
1'
#123000
0'
#123500
b100 4
b1111100 5
b1111101 )
b1111100 8
1'
#124000
0'
#124500
b101 4
b1111101 5
b1111110 )
b1111101 8
1'
#125000
0'
#125500
b110 4
b1111110 5
b1111111 )
b1111110 8
1'
#126000
0'
#126500
b111 4
b1111111 5
b10000000 )
b1111111 8
1'
#127000
0'
#127500
b1000 4
b10000000 5
b10000001 )
b10000000 8
1'
#128000
0'
#128500
b1001 4
0+
b10000001 5
b10000010 )
b10000001 8
1'
#129000
0'
#129500
b1010 4
b101110 1
b10000010 5
b10000011 )
b10000010 8
1'
#130000
0'
#130500
b1011 4
b101111 1
b10000011 5
b10000100 )
b10000011 8
1'
#131000
0'
#131500
b1100 4
b110000 1
b10000100 5
b10000101 )
b10000100 8
1'
#132000
0'
#132500
b1101 4
b110001 1
b10000101 5
b10000110 )
b10000101 8
1'
#133000
0'
#133500
b1110 4
b110010 1
b10000110 5
b10000111 )
b10000110 8
1'
#134000
0'
#134500
b1111 4
b110011 1
b10000111 5
b10001000 )
b10000111 8
1'
#135000
0'
#135500
b10000 4
b110100 1
b10001000 5
b10001001 )
b10001000 8
1'
#136000
0'
#136500
b10001 4
b110101 1
b10001001 5
b10001010 )
b10001001 8
1'
#137000
0'
#137500
b10010 4
b110110 1
b10001010 5
b10001011 )
b10001010 8
1'
#138000
0'
#138500
1$
b10011 4
b110111 1
b10001011 5
b10001100 )
b10001011 8
1'
#139000
0'
#139500
b10100 4
b111000 1
b10001100 5
b10001101 )
b10001100 8
1'
#140000
0'
#140500
b10101 4
b111001 1
b10001101 5
b10001110 )
b10001101 8
1'
#141000
0'
#141500
b10110 4
b111010 1
b10001110 5
b10001111 )
b10001110 8
1'
#142000
0'
#142500
b10111 4
b111011 1
b10001111 5
b10010000 )
b10001111 8
1'
#143000
0'
#143500
0$
b1 "
b1 /
b11000 4
b0 1
b1 0
b10010000 5
b10010001 )
b10010000 8
1'
#144000
0'
#144500
b10 !
b10 2
b0 4
b10 3
b1 1
b10010001 5
b10010010 )
b10010001 8
1'
#145000
0'
#145500
b1 4
b10 1
b10010010 5
b10010011 )
b10010010 8
1'
#146000
0'
#146500
b10 4
b11 1
b10010011 5
b10010100 )
b10010011 8
1'
#147000
0'
#147500
b11 4
b100 1
b10010100 5
b10010101 )
b10010100 8
1'
#148000
0'
#148500
b100 4
b101 1
b10010101 5
b10010110 )
b10010101 8
1'
#149000
0'
#149500
b0 !
b0 2
b0 4
b0 3
b110 1
b10010110 5
b10010110 8
1'
